{
  "line1": {
    "2025-10-14": {
      "field1": "80.0",
      "field2": "80.0",
      "field3": "80.0",
      "field4": "80.0",
      "field5": "79.0",
      "field6": "80.0",
      "field7": "80.0",
      "field8": "80.0",
      "field9": "80.0"
    },
    "2025-11-10": {
      "field1": "80.0",
      "field2": "80.0",
      "field3": "80.0",
      "field4": "80.0",
      "field5": "79.0",
      "field6": "80.0",
      "field7": "80.0",
      "field8": "80.0",
      "field9": "80.0"
    }
  },
  "line2": {
    "2025-10-27": {
      "field1": "79.0",
      "field2": "80.0",
      "field3": "80.0",
      "field4": "80.0",
      "field5": "79.0",
      "field6": "80.0",
      "field7": "80.0",
      "field8": "80.0",
      "field9": "80.0"
    },
    "2025-11-19": {
      "field1": "79.0",
      "field2": "80.0",
      "field3": "80.0",
      "field4": "80.0",
      "field5": "79.0",
      "field6": "80.0",
      "field7": "80.0",
      "field8": "80.0"
    }
  },
  "line3": {
    "2025-10-06": {
      "field1": "79.1",
      "field2": "80.0",
      "field3": "80.0",
      "field4": "80.0",
      "field5": "80.0",
      "field6": "80.0",
      "field7": "80.0",
      "field8": "80.0",
      "field9": "80.0"
    },
    "2025-10-20": {
      "field1": "79.1",
      "field2": "80.0",
      "field3": "80.0",
      "field4": "80.0",
      "field5": "80.0",
      "field6": "80.0",
      "field7": "80.0",
      "field8": "80.0",
      "field9": "80.0"
    }
  }
}